ob_dj_payment_tap/apis/__init__.py
ob_dj_payment_tap/apis/payment_tap/__init__.py
ob_dj_payment_tap/apis/payment_tap/serializers.py
ob_dj_payment_tap/apis/payment_tap/urls.py
ob_dj_payment_tap/apis/payment_tap/views.py
ob_dj_payment_tap/core/__init__.py
ob_dj_payment_tap/core/payment_tap/__init__.py
ob_dj_payment_tap/core/payment_tap/admin.py
ob_dj_payment_tap/core/payment_tap/apps.py
ob_dj_payment_tap/core/payment_tap/managers.py
ob_dj_payment_tap/core/payment_tap/models.py
ob_dj_payment_tap/core/payment_tap/settings_validation.py
ob_dj_payment_tap/core/payment_tap/tasks.py
ob_dj_payment_tap/core/payment_tap/utils.py
ob_dj_payment_tap/core/payment_tap/migrations/0001_initial.py
ob_dj_payment_tap/core/payment_tap/migrations/__init__.py
ob_dj_payment_tap-0.0.4.dist-info/METADATA
ob_dj_payment_tap-0.0.4.dist-info/WHEEL
ob_dj_payment_tap-0.0.4.dist-info/top_level.txt
ob_dj_payment_tap-0.0.4.dist-info/RECORD
