Metadata-Version: 2.1
Name: ob-dj-payment-tap
Version: 0.0.4
Summary: OBytes Django application for managing payment processing with TAP.
Home-page: https://www.obytes.com/
Author: OBytes
Author-email: hello@obytes.com
License: BSD-3-Clause
Platform: UNKNOWN
Classifier: Environment :: Web Environment
Classifier: Framework :: Django
Classifier: Intended Audience :: Developers
Classifier: License :: OSI Approved :: BSD License
Classifier: Operating System :: OS Independent
Classifier: Programming Language :: Python
Classifier: Programming Language :: Python :: 3
Classifier: Programming Language :: Python :: 3 :: Only
Classifier: Programming Language :: Python :: 3.8
Classifier: Topic :: Internet :: WWW/HTTP
Classifier: Topic :: Internet :: WWW/HTTP :: Dynamic Content
Requires-Python: >=3.8
Requires-Dist: django
Requires-Dist: djangorestframework
Requires-Dist: django-cryptography
Requires-Dist: cryptography
